[{"id":"cmg0w4vsw0000w5pkuanhl2iu","title":"ჩვენ შესახებ","content":{"sections":[{"id":"1","type":"text","content":"EduArena არის თანამედროვე საგანმანათლებლო პლატფორმა, რომელიც მოსწავლეებს სთავაზობს ონლაინ ოლიმპიადებს სხვადასხვა საგანში. თითოეული ოლიმპიადა გათვლილია შესაბამისი კლასის პროგრამაზე, რაც უზრუნველყოფს სამართლიან და თანაბარ პირობებს მონაწილეებისთვის. მოსწავლეს შეუძლია ოლიმპიადაში მონაწილეობა მიიღოს ონლაინ, სახლიდან გაუსვლელად, რაც კიდევ უფრო მოსახერხებელს და ხელმისაწვდომს ხდის პროცესს."},{"id":"2","type":"list","items":["განათლების ხელმისაწვდომობის გაზრდა;","ინოვაციური ტექნოლოგიების დანერგვა სასწავლო პროცესში;","მოსწავლეების მოტივაციის გაძლიერება ჯანსაღი კონკურსებისა და ოლიმპიადების საშუალებით."],"title":"ჩვენი მისიაა:"},{"id":"3","type":"list","items":["მრავალფეროვანი ოლიმპიადებით სხვადასხვა საგნისა და კლასის მიხედვით;","გამჭვირვალე და ობიექტური შეფასების სისტემით;","თანამედროვე, მარტივად გამოსაყენებელი პლატფორმით."],"title":"EduArena გამოირჩევა:"},{"id":"4","type":"text","content":"ჩვენ გვჯერა, რომ განათლების პროცესში ტექნოლოგიების ინტეგრაცია მნიშვნელოვნად ზრდის მოსწავლეთა ინტერესს და აძლევს მათ შესაძლებლობას, საკუთარი ცოდნა რეალურ გარემოში გამოსცადონ."}]},"createdAt":"2025-09-26 13:41:43.04","updatedAt":"2025-10-08 19:24:16.159"}]